session_request/__init__.py
session_request/session_request.py
session_request/version.py
session_request-0.0.4.dist-info/METADATA
session_request-0.0.4.dist-info/WHEEL
session_request-0.0.4.dist-info/top_level.txt
session_request-0.0.4.dist-info/zip-safe
session_request-0.0.4.dist-info/RECORD
