Metadata-Version: 2.1
Name: session-request
Version: 0.0.4
Summary: a http request class
Home-page: https://github.com/mouday/session-request
Author: Peng Shiyu
Author-email: pengshiyuyx@gmail.com
License: MIT
Keywords: session,request,http,api
Platform: UNKNOWN
Classifier: Programming Language :: Python :: 3
